drf_eagerloading/__init__.py
drf_eagerloading/mixins.py
drf_eagerloading/utils.py
drf_eagerloading-0.0.3.dist-info/METADATA
drf_eagerloading-0.0.3.dist-info/RECORD
drf_eagerloading-0.0.3.dist-info/WHEEL
drf_eagerloading-0.0.3.dist-info/top_level.txt
