Metadata-Version: 2.1
Name: drf-eagerloading
Version: 0.0.3
Summary: Calculate prefetch_related and select_related recursively based on the definition on the serializers.
Home-page: https://github.com/talpor/drf_eagerloading
Author: Pedro Piñango
Author-email: ppinango@talpor.com
License: MIT license
Keywords: drf_eagerloading
Platform: UNKNOWN
Classifier: Development Status :: 2 - Pre-Alpha
Classifier: Environment :: Web Environment
Classifier: Framework :: Django :: 2.0
Classifier: Framework :: Django :: 2.1
Classifier: Framework :: Django
Classifier: Intended Audience :: Developers
Classifier: License :: OSI Approved :: MIT License
Classifier: Natural Language :: English
Classifier: Operating System :: OS Independent
Classifier: Programming Language :: Python :: 3
Classifier: Programming Language :: Python :: 3.6
Classifier: Programming Language :: Python :: 3.7
Requires-Python: >=3.6
